100-Days-of-SystemVerilog/Day08_Bus_Protocols/src/axil_registers.sv
module axil_registers (
    input  logic clk, rst_n,
    input  logic [31:0] s_axi_awaddr,
    input  logic s_axi_awvalid,
    output logic s_axi_awready,
    input  logic [31:0] s_axi_wdata,
    input  logic s_axi_wvalid,
    output logic s_axi_wready,
    output logic [1:0] s_axi_bresp,
    output logic s_axi_bvalid,
    input  logic s_axi_bready
);
    logic [31:0] control_reg;

    assign s_axi_awready = 1'b1;
    assign s_axi_wready  = 1'b1;
    assign s_axi_bresp   = 2'b00;

    logic write_happening;
    assign write_happening = s_axi_awvalid && s_axi_awready && s_axi_wvalid && s_axi_wready;

    always_ff @(posedge clk or negedge rst_n) begin
        if (!rst_n) begin
            control_reg <= 0;
            s_axi_bvalid <= 0;
        end else begin
            if (write_happening) begin
                control_reg <= s_axi_wdata; 
                s_axi_bvalid <= 1;          
            end else if (s_axi_bvalid && s_axi_bready) begin
                s_axi_bvalid <= 0;  
            end
        end
    end
endmodule

100-Days-of-SystemVerilog/Day08_Bus_Protocols/src/axis_slave.sv
module axis_slave #(parameter WIDTH = 32) (
    input  logic clk, rst_n,
    input  logic s_tvalid,
    output logic s_tready,
    input  logic [WIDTH-1:0] s_tdata,
    input  logic s_tlast,
    input  logic internal_fifo_full
);
    assign s_tready = !internal_fifo_full;

    always_ff @(posedge clk or negedge rst_n) begin
        if (!rst_n) begin
            // Reset logic
        end else if (s_tvalid && s_tready) begin
            
            if (s_tlast) begin
                // End of packet processing (e.g., verify CRC)
            end
        end
    end
endmodule

100-Days-of-SystemVerilog/Day08_Bus_Protocols/src/axis_master.sv
module axis_master #(parameter WIDTH = 32, PKT_LEN = 4) (
    input  logic clk, rst_n,
    input  logic start_tx, 
    output logic m_tvalid,
    input  logic m_tready,
    output logic [WIDTH-1:0] m_tdata,
    output logic m_tlast
);
    logic [7:0] count;
    logic active;

    always_ff @(posedge clk or negedge rst_n) begin
        if (!rst_n) begin
            m_tvalid <= 0;
            m_tdata  <= 0;
            m_tlast  <= 0;
            count    <= 0;
            active   <= 0;
        end else begin
            if (start_tx && !active) begin
                active   <= 1;
                m_tvalid <= 1;
                m_tdata  <= 32'hAAAA_0000;
                count    <= 1;
                m_tlast  <= 0;
            end else if (active && m_tready && m_tvalid) begin
                if (count == PKT_LEN - 1) begin
                    m_tlast <= 1;
                end
                
                if (count == PKT_LEN) begin
                    // Packet complete
                    active   <= 0;
                    m_tvalid <= 0;
                    m_tlast  <= 0;
                end else begin
                    m_tdata <= m_tdata + 1'b1;
                    count   <= count + 1'b1;
                end
            end
        end
    end
endmodule

100-Days-of-SystemVerilog/Day08_Bus_Protocols/src/apb_slave.sv
module apb_slave (
    input  logic pclk, presetn,
    input  logic psel,     
    input  logic penable,  
    input  logic pwrite,   
    input  logic [31:0] paddr,
    input  logic [31:0] pwdata,
    output logic [31:0] prdata,
    output logic pready  
);
    
    logic [31:0] reg0, reg1, reg2, reg3;
    always_ff @(posedge pclk or negedge presetn) begin
        if (!presetn) begin
            reg0 <= 0; reg1 <= 0; reg2 <= 0; reg3 <= 0;
        end else if (psel && penable && pwrite) begin
            case (paddr[3:2]) 
                2'b00: reg0 <= pwdata;
                2'b01: reg1 <= pwdata;
                2'b10: reg2 <= pwdata;
                2'b11: reg3 <= pwdata;
            endcase
        end
    end

    always_comb begin
        prdata = 32'h00000000;
        if (psel && !pwrite) begin
            case (paddr[3:2])
                2'b00: prdata = reg0;
                2'b01: prdata = reg1;
                2'b10: prdata = reg2;
                2'b11: prdata = reg3;
            endcase
        end
    end
    assign pready = 1'b1;
endmodule

100-Days-of-SystemVerilog/Day08_Bus_Protocols/src/skid_buffer.sv
module skid_buffer #(parameter WIDTH = 32) (
    input  logic clk, rst_n,
    input  logic             s_valid,
    output logic             s_ready,
    input  logic [WIDTH-1:0] s_data,
    output logic             m_valid,
    input  logic             m_ready,
    output logic [WIDTH-1:0] m_data
);
    logic [WIDTH-1:0] skid_data;
    logic             skid_valid;
    assign s_ready = !skid_valid || m_ready;

    always_ff @(posedge clk or negedge rst_n) begin
        if (!rst_n) begin
            m_valid    <= 0;
            skid_valid <= 0;
            m_data     <= 0;
            skid_data  <= 0;
        end else begin
            if (m_ready || !m_valid) begin
                m_valid <= s_valid || skid_valid;
                if (skid_valid) begin
                    m_data <= skid_data;    
                    skid_valid <= 0;
                end else if (s_valid) begin
                    m_data <= s_data;       
                end
            end else if (s_valid && s_ready) begin
                skid_valid <= 1;
                skid_data  <= s_data;        
            end
        end
    end
endmodule

100-Days-of-SystemVerilog/Day08_Bus_Protocols/tb/tb_day8.sv
`timescale 1ns / 1ps

module tb_day8;

  // ==========================================
  // 1. CLOCK & RESET
  // ==========================================
  logic clk = 0;
  logic rst_n;
  always #5 clk = ~clk; // 100MHz clock

  // ==========================================
  // 2. SIGNAL DECLARATIONS
  // ==========================================
  // 71. Skid Buffer
  logic sb_s_valid, sb_s_ready;
  logic [31:0] sb_s_data;
  logic sb_m_valid, sb_m_ready;
  logic [31:0] sb_m_data;

  // 72. APB Slave
  logic apb_psel, apb_penable, apb_pwrite, apb_pready;
  logic [31:0] apb_paddr, apb_pwdata, apb_prdata;

  // 73 & 74. AXI-Stream (Master -> Slave)
  logic axis_start;
  logic axis_tvalid, axis_tready, axis_tlast;
  logic [31:0] axis_tdata;
  logic rx_fifo_full;

  // 75. AXI4-Lite Registers
  logic axil_awvalid, axil_awready;
  logic [31:0] axil_awaddr;
  logic axil_wvalid, axil_wready;
  logic [31:0] axil_wdata;
  logic axil_bvalid, axil_bready;
  logic [1:0] axil_bresp;

  // ==========================================
  // 3. DUT INSTANTIATIONS
  // ==========================================
  skid_buffer #(32) dut71 (
      .clk(clk), .rst_n(rst_n),
      .s_valid(sb_s_valid), .s_ready(sb_s_ready), .s_data(sb_s_data),
      .m_valid(sb_m_valid), .m_ready(sb_m_ready), .m_data(sb_m_data)
  );

  apb_slave dut72 (
      .pclk(clk), .presetn(rst_n),
      .psel(apb_psel), .penable(apb_penable), .pwrite(apb_pwrite),
      .paddr(apb_paddr), .pwdata(apb_pwdata), .prdata(apb_prdata), .pready(apb_pready)
  );

  // Connect Master directly to Slave!
  axis_master #(32, 4) dut73 (
      .clk(clk), .rst_n(rst_n), .start_tx(axis_start),
      .m_tvalid(axis_tvalid), .m_tready(axis_tready), .m_tdata(axis_tdata), .m_tlast(axis_tlast)
  );

  axis_slave #(32) dut74 (
      .clk(clk), .rst_n(rst_n),
      .s_tvalid(axis_tvalid), .s_tready(axis_tready), .s_tdata(axis_tdata), .s_tlast(axis_tlast),
      .internal_fifo_full(rx_fifo_full)
  );

  axil_registers dut75 (
      .clk(clk), .rst_n(rst_n),
      .s_axi_awaddr(axil_awaddr), .s_axi_awvalid(axil_awvalid), .s_axi_awready(axil_awready),
      .s_axi_wdata(axil_wdata), .s_axi_wvalid(axil_wvalid), .s_axi_wready(axil_wready),
      .s_axi_bresp(axil_bresp), .s_axi_bvalid(axil_bvalid), .s_axi_bready(axil_bready)
  );

  // ==========================================
  // 4. STIMULUS GENERATION
  // ==========================================
  initial begin
    $dumpfile("day8_sim.vcd");
    $dumpvars(0, tb_day8);

    // Initialize all inputs
    rst_n = 0;
    sb_s_valid = 0; sb_s_data = 0; sb_m_ready = 1;
    apb_psel = 0; apb_penable = 0; apb_pwrite = 0; apb_paddr = 0; apb_pwdata = 0;
    axis_start = 0; rx_fifo_full = 0;
    axil_awvalid = 0; axil_awaddr = 0; axil_wvalid = 0; axil_wdata = 0; axil_bready = 0;

    #25 rst_n = 1;

    $display("\n=======================================");
    $display("STARTING DAY 8: AMBA BUS PROTOCOLS");
    $display("=======================================\n");

    // --- 71. Skid Buffer Test ---
    $display(">> Testing Skid Buffer Stall Recovery...");
    @(posedge clk);
    sb_s_valid = 1; sb_s_data = 32'hAAAA; sb_m_ready = 0; // Downstream Stalls!
    @(posedge clk);
    sb_s_valid = 1; sb_s_data = 32'hBBBB; // Send next data while stalled
    @(posedge clk);
    sb_s_valid = 0; sb_m_ready = 1;       // Downstream Recovers
    @(posedge clk);
    @(posedge clk);

    // --- 72. APB Slave Test ---
    $display(">> Writing 0xDEADBEEF to APB Register 1...");
    @(posedge clk);
    // SETUP Phase
    apb_psel = 1; apb_pwrite = 1; apb_paddr = 32'h00000004; apb_pwdata = 32'hDEADBEEF;
    @(posedge clk);
    // ACCESS Phase
    apb_penable = 1;
    wait(apb_pready);
    @(posedge clk);
    apb_psel = 0; apb_penable = 0; apb_pwrite = 0;

    // --- 73 & 74. AXI-Stream Handshake Test ---
    $display(">> Initiating 4-beat AXI-Stream Packet Transfer...");
    @(posedge clk);
    axis_start = 1; 
    @(posedge clk); 
    axis_start = 0;
    
    // Intentionally stall the receiver on cycle 2 to test backpressure
    @(posedge clk);
    rx_fifo_full = 1; 
    $display("   [!] Receiver FIFO Full. Halting Bus...");
    #20;
    rx_fifo_full = 0;
    $display("   [!] Receiver Recovered. Resuming...");
    
    wait(axis_tlast); // Wait for the end of the packet
    @(posedge clk);

    // --- 75. AXI4-Lite Register Test ---
    $display(">> Performing AXI4-Lite Write Transaction...");
    @(posedge clk);
    // 1. Provide Address & Data
    axil_awvalid = 1; axil_awaddr = 32'h10;
    axil_wvalid  = 1; axil_wdata  = 32'hCAFEBABE;
    
    // 2. Wait for slave to accept Address & Data
    wait(axil_awready && axil_wready);
    @(posedge clk);
    axil_awvalid = 0; axil_wvalid = 0;
    
    // 3. Wait for Write Response (B-Channel)
    wait(axil_bvalid);
    axil_bready = 1; // Master accepts response
    @(posedge clk);
    axil_bready = 0;

    #50;
    $display("\n=======================================");
    $display("DAY 8 TESTS COMPLETED SUCCESSFULLY ");
    $display("=======================================\n");
    
    $finish;
  end

endmodule

100-Days-of-SystemVerilog/Day08_Bus_Protocols/day8_sim.vcd
$date
	Wed May 27 17:54:05 2026
$end
$version
	Icarus Verilog
$end
$timescale
	1ps
$end
$scope module tb_day8 $end
$var wire 1 ! apb_pready $end
$var wire 1 " axil_awready $end
$var wire 2 # axil_bresp [1:0] $end
$var wire 1 $ axil_wready $end
$var wire 1 % sb_s_ready $end
$var wire 1 & sb_m_valid $end
$var wire 32 ' sb_m_data [31:0] $end
$var wire 1 ( axis_tvalid $end
$var wire 1 ) axis_tready $end
$var wire 1 * axis_tlast $end
$var wire 32 + axis_tdata [31:0] $end
$var wire 1 , axil_bvalid $end
$var wire 32 - apb_prdata [31:0] $end
$var reg 32 . apb_paddr [31:0] $end
$var reg 1 / apb_penable $end
$var reg 1 0 apb_psel $end
$var reg 32 1 apb_pwdata [31:0] $end
$var reg 1 2 apb_pwrite $end
$var reg 32 3 axil_awaddr [31:0] $end
$var reg 1 4 axil_awvalid $end
$var reg 1 5 axil_bready $end
$var reg 32 6 axil_wdata [31:0] $end
$var reg 1 7 axil_wvalid $end
$var reg 1 8 axis_start $end
$var reg 1 9 clk $end
$var reg 1 : rst_n $end
$var reg 1 ; rx_fifo_full $end
$var reg 1 < sb_m_ready $end
$var reg 32 = sb_s_data [31:0] $end
$var reg 1 > sb_s_valid $end
$scope module dut71 $end
$var wire 1 9 clk $end
$var wire 1 < m_ready $end
$var wire 1 : rst_n $end
$var wire 32 ? s_data [31:0] $end
$var wire 1 % s_ready $end
$var wire 1 > s_valid $end
$var reg 32 @ m_data [31:0] $end
$var reg 1 & m_valid $end
$var reg 32 A skid_data [31:0] $end
$var reg 1 B skid_valid $end
$upscope $end
$scope module dut72 $end
$var wire 32 C paddr [31:0] $end
$var wire 1 9 pclk $end
$var wire 1 / penable $end
$var wire 1 ! pready $end
$var wire 1 : presetn $end
$var wire 1 0 psel $end
$var wire 32 D pwdata [31:0] $end
$var wire 1 2 pwrite $end
$var reg 32 E prdata [31:0] $end
$var reg 32 F reg0 [31:0] $end
$var reg 32 G reg1 [31:0] $end
$var reg 32 H reg2 [31:0] $end
$var reg 32 I reg3 [31:0] $end
$upscope $end
$scope module dut73 $end
$var wire 1 9 clk $end
$var wire 1 : rst_n $end
$var wire 1 8 start_tx $end
$var wire 1 ) m_tready $end
$var reg 1 J active $end
$var reg 8 K count [7:0] $end
$var reg 32 L m_tdata [31:0] $end
$var reg 1 * m_tlast $end
$var reg 1 ( m_tvalid $end
$upscope $end
$scope module dut74 $end
$var wire 1 9 clk $end
$var wire 1 ; internal_fifo_full $end
$var wire 1 : rst_n $end
$var wire 32 M s_tdata [31:0] $end
$var wire 1 * s_tlast $end
$var wire 1 ( s_tvalid $end
$var wire 1 ) s_tready $end
$upscope $end
$scope module dut75 $end
$var wire 1 9 clk $end
$var wire 1 : rst_n $end
$var wire 32 N s_axi_awaddr [31:0] $end
$var wire 1 " s_axi_awready $end
$var wire 1 4 s_axi_awvalid $end
$var wire 1 5 s_axi_bready $end
$var wire 2 O s_axi_bresp [1:0] $end
$var wire 32 P s_axi_wdata [31:0] $end
$var wire 1 $ s_axi_wready $end
$var wire 1 7 s_axi_wvalid $end
$var wire 1 Q write_happening $end
$var reg 32 R control_reg [31:0] $end
$var reg 1 , s_axi_bvalid $end
$upscope $end
$upscope $end
$enddefinitions $end
#0
$dumpvars
b0 R
0Q
b0 P
b0 O
b0 N
b0 M
b0 L
b0 K
0J
b0 I
b0 H
b0 G
b0 F
b0 E
b0 D
b0 C
0B
b0 A
b0 @
b0 ?
0>
b0 =
1<
0;
0:
09
08
07
b0 6
05
04
b0 3
02
b0 1
00
0/
b0 .
b0 -
0,
b0 +
0*
1)
0(
b0 '
0&
1%
1$
b0 #
1"
1!
$end
#5000
19
#10000
09
#15000
19
#20000
09
#25000
b1010101010101010 '
b1010101010101010 @
1&
0<
b1010101010101010 =
b1010101010101010 ?
1>
19
1:
#30000
09
#35000
0%
b1011101110111011 A
1B
b1011101110111011 =
b1011101110111011 ?
19
#40000
09
#45000
0B
b1011101110111011 '
b1011101110111011 @
1%
1<
0>
19
#50000
09
#55000
0&
19
#60000
09
#65000
19
#70000
09
#75000
b11011110101011011011111011101111 1
b11011110101011011011111011101111 D
b100 .
b100 C
12
10
19
#80000
09
#85000
b11011110101011011011111011101111 G
1/
19
#90000
09
#95000
02
0/
00
19
#100000
09
#105000
b1 K
b10101010101010100000000000000000 +
b10101010101010100000000000000000 L
b10101010101010100000000000000000 M
1(
1J
18
19
#110000
09
#115000
b10 K
b10101010101010100000000000000001 +
b10101010101010100000000000000001 L
b10101010101010100000000000000001 M
08
19
#120000
09
#125000
0)
1;
19
#130000
09
#135000
19
#140000
09
#145000
b11 K
b10101010101010100000000000000010 +
b10101010101010100000000000000010 L
b10101010101010100000000000000010 M
19
1)
0;
#150000
09
#155000
b100 K
b10101010101010100000000000000011 +
b10101010101010100000000000000011 L
b10101010101010100000000000000011 M
1*
19
#160000
09
#165000
0*
0(
0J
19
#170000
09
#175000
1Q
b11001010111111101011101010111110 6
b11001010111111101011101010111110 P
17
b10000 3
b10000 N
14
19
#180000
09
#185000
15
1,
b11001010111111101011101010111110 R
0Q
07
04
19
#190000
09
#195000
05
19
