100-Days-of-SystemVerilog/Day07_CDC_Arbitration/src/crossbar_4x4.sv
module crossbar_4x4 #(parameter WIDTH = 32) (
    input  logic [WIDTH-1:0] in0, in1, in2, in3,
    input  logic [1:0] sel0, sel1, sel2, sel3, // Which input routes to each output
    output logic [WIDTH-1:0] out0, out1, out2, out3
);
    // Route to Output 0
    always_comb begin
        case (sel0)
            2'b00: out0 = in0;
            2'b01: out0 = in1;
            2'b10: out0 = in2;
            2'b11: out0 = in3;
        endcase
    end

    // Route to Output 1
    always_comb begin
        case (sel1)
            2'b00: out1 = in0;
            2'b01: out1 = in1;
            2'b10: out1 = in2;
            2'b11: out1 = in3;
        endcase
    end

    // Route to Output 2
    always_comb begin
        case (sel2)
            2'b00: out2 = in0;
            2'b01: out2 = in1;
            2'b10: out2 = in2;
            2'b11: out2 = in3;
        endcase
    end

    // Route to Output 3
    always_comb begin
        case (sel3)
            2'b00: out3 = in0;
            2'b01: out3 = in1;
            2'b10: out3 = in2;
            2'b11: out3 = in3;
        endcase
    end
endmodule

100-Days-of-SystemVerilog/Day07_CDC_Arbitration/src/matrix_arbiter.sv
module matrix_arbiter (
    input  logic clk, rst_n,
    input  logic [3:0] req,
    output logic [3:0] grant
);
    // 4x4 Priority Matrix: matrix[i][j] = 1 means i has priority over j
    logic [3:0] matrix [0:3];
    logic [3:0] wins;

    // Combinational Grant Logic
    always_comb begin
        grant = 4'b0000;
        wins[0] = req[0] & (matrix[0][1] | ~req[1]) & (matrix[0][2] | ~req[2]) & (matrix[0][3] | ~req[3]);
        wins[1] = req[1] & (matrix[1][0] | ~req[0]) & (matrix[1][2] | ~req[2]) & (matrix[1][3] | ~req[3]);
        wins[2] = req[2] & (matrix[2][0] | ~req[0]) & (matrix[2][1] | ~req[1]) & (matrix[2][3] | ~req[3]);
        wins[3] = req[3] & (matrix[3][0] | ~req[0]) & (matrix[3][1] | ~req[1]) & (matrix[3][2] | ~req[2]);

        // Break ties securely (fallback fixed priority)
        if      (wins[0]) grant[0] = 1'b1;
        else if (wins[1]) grant[1] = 1'b1;
        else if (wins[2]) grant[2] = 1'b1;
        else if (wins[3]) grant[3] = 1'b1;
    end

    // Sequential Matrix Update
    always_ff @(posedge clk or negedge rst_n) begin
        if (!rst_n) begin
            // Initialize upper triangle to 1 (0 beats 1, 1 beats 2, etc.)
            matrix[0] <= 4'b1110;
            matrix[1] <= 4'b1100;
            matrix[2] <= 4'b1000;
            matrix[3] <= 4'b0000;
        end else if (grant != 0) begin
            // If a device gets the grant, it loses priority against everyone else
            if (grant[0]) begin matrix[0] <= 4'b0000; matrix[1][0] <= 1; matrix[2][0] <= 1; matrix[3][0] <= 1; end
            if (grant[1]) begin matrix[1] <= 4'b0000; matrix[0][1] <= 1; matrix[2][1] <= 1; matrix[3][1] <= 1; end
            if (grant[2]) begin matrix[2] <= 4'b0000; matrix[0][2] <= 1; matrix[1][2] <= 1; matrix[3][2] <= 1; end
            if (grant[3]) begin matrix[3] <= 4'b0000; matrix[0][3] <= 1; matrix[1][3] <= 1; matrix[2][3] <= 1; end
        end
    end
endmodule

100-Days-of-SystemVerilog/Day07_CDC_Arbitration/src/async_fifo.sv
module async_fifo #(parameter DEPTH_LOG2 = 4, WIDTH = 8) (
    // Write Domain
    input  logic wr_clk, wr_rst_n, wr_en,
    input  logic [WIDTH-1:0] wr_data,
    output logic full,
    
    // Read Domain
    input  logic rd_clk, rd_rst_n, rd_en,
    output logic [WIDTH-1:0] rd_data,
    output logic empty
);
    localparam DEPTH = 1 << DEPTH_LOG2;
    logic [WIDTH-1:0] memory [0:DEPTH-1];

    logic [DEPTH_LOG2:0] wr_ptr_bin, wr_ptr_gray, wr_ptr_gray_next;
    logic [DEPTH_LOG2:0] rd_ptr_bin, rd_ptr_gray, rd_ptr_gray_next;
    
    logic [DEPTH_LOG2:0] wr_ptr_gray_sync1, wr_ptr_gray_sync2;
    logic [DEPTH_LOG2:0] rd_ptr_gray_sync1, rd_ptr_gray_sync2;

    // --- WRITE DOMAIN LOGIC ---
    always_comb begin
        wr_ptr_gray_next = (wr_ptr_bin + 1'b1) ^ ((wr_ptr_bin + 1'b1) >> 1);
    end

    always_ff @(posedge wr_clk or negedge wr_rst_n) begin
        if (!wr_rst_n) begin
            wr_ptr_bin <= 0; wr_ptr_gray <= 0;
        end else if (wr_en && !full) begin
            memory[wr_ptr_bin[DEPTH_LOG2-1:0]] <= wr_data;
            wr_ptr_bin <= wr_ptr_bin + 1'b1;
            wr_ptr_gray <= wr_ptr_gray_next;
        end
    end

    // Sync Read Pointer into Write Domain
    always_ff @(posedge wr_clk or negedge wr_rst_n) begin
        if (!wr_rst_n) begin
            rd_ptr_gray_sync1 <= 0; rd_ptr_gray_sync2 <= 0;
        end else begin
            rd_ptr_gray_sync1 <= rd_ptr_gray;
            rd_ptr_gray_sync2 <= rd_ptr_gray_sync1;
        end
    end
    
    // Full condition: MSB and 2nd MSB differ, rest match (in Gray code)
    assign full = (wr_ptr_gray == {~rd_ptr_gray_sync2[DEPTH_LOG2:DEPTH_LOG2-1], 
                                    rd_ptr_gray_sync2[DEPTH_LOG2-2:0]});

    // --- READ DOMAIN LOGIC ---
    always_comb begin
        rd_ptr_gray_next = (rd_ptr_bin + 1'b1) ^ ((rd_ptr_bin + 1'b1) >> 1);
    end

    always_ff @(posedge rd_clk or negedge rd_rst_n) begin
        if (!rd_rst_n) begin
            rd_ptr_bin <= 0; rd_ptr_gray <= 0; rd_data <= 0;
        end else if (rd_en && !empty) begin
            rd_data <= memory[rd_ptr_bin[DEPTH_LOG2-1:0]];
            rd_ptr_bin <= rd_ptr_bin + 1'b1;
            rd_ptr_gray <= rd_ptr_gray_next;
        end
    end

    // Sync Write Pointer into Read Domain
    always_ff @(posedge rd_clk or negedge rd_rst_n) begin
        if (!rd_rst_n) begin
            wr_ptr_gray_sync1 <= 0; wr_ptr_gray_sync2 <= 0;
        end else begin
            wr_ptr_gray_sync1 <= wr_ptr_gray;
            wr_ptr_gray_sync2 <= wr_ptr_gray_sync1;
        end
    end
    
    // Empty condition: Pointers are exactly identical
    assign empty = (rd_ptr_gray == wr_ptr_gray_sync2);

endmodule

100-Days-of-SystemVerilog/Day07_CDC_Arbitration/src/handshake_sync.sv
module handshake_sync #(parameter WIDTH = 8) (
    input  logic clk_src, rst_n_src,
    input  logic req_in,
    input  logic [WIDTH-1:0] data_in,
    output logic ready_src,         // Tells source we are ready for new data
    
    input  logic clk_dest, rst_n_dest,
    input  logic ack_dest,          // Destination says it read the data
    output logic req_dest,
    output logic [WIDTH-1:0] data_out
);
    logic req_sync1, req_sync2;
    logic ack_sync1, ack_sync2;
    
    // Source Domain: Synchronize ACK back from Destination
    always_ff @(posedge clk_src or negedge rst_n_src) begin
        if (!rst_n_src) begin
            ack_sync1 <= 0; ack_sync2 <= 0;
        end else begin
            ack_sync1 <= ack_dest; ack_sync2 <= ack_sync1;
        end
    end
    
    // Source is ready when the handshake is fully complete (req_in and ack_sync2 are both 0)
    assign ready_src = ~req_in & ~ack_sync2;

    // Destination Domain: Synchronize REQ from Source
    always_ff @(posedge clk_dest or negedge rst_n_dest) begin
        if (!rst_n_dest) begin
            req_sync1 <= 0; req_sync2 <= 0; data_out <= 0;
        end else begin
            req_sync1 <= req_in; req_sync2 <= req_sync1;
            
            // Latch data when REQ safely arrives
            if (req_sync2 && !ack_dest) begin
                data_out <= data_in;
            end
        end
    end
    
    assign req_dest = req_sync2;
endmodule

100-Days-of-SystemVerilog/Day07_CDC_Arbitration/tb/tb_day7.sv
`timescale 1ns / 1ps

module tb_day7;

  // ==========================================
  // 1. CLOCKS & RESETS (DUAL DOMAIN!)
  // ==========================================
  logic clk_fast = 0; // 500MHz (2ns period)
  logic clk_slow = 0; // 100MHz (10ns period)
  logic rst_n;

  always #1 clk_fast = ~clk_fast;
  always #5 clk_slow = ~clk_slow;

  // ==========================================
  // 2. SIGNAL DECLARATIONS
  // ==========================================
  // 63. Handshake Synchronizer
  logic hs_req_in, hs_ready_src, hs_ack_dest, hs_req_dest;
  logic [7:0] hs_data_in, hs_data_out;

  // 66. Asynchronous FIFO
  logic fifo_wr_en, fifo_full;
  logic [7:0] fifo_wr_data;
  logic fifo_rd_en, fifo_empty;
  logic [7:0] fifo_rd_data;

  // 69. Matrix Arbiter (LRU)
  logic [3:0] arb_req, arb_grant;

  // 70. 4x4 Crossbar
  logic [31:0] xb_in0, xb_in1, xb_in2, xb_in3;
  logic [1:0]  xb_sel0, xb_sel1, xb_sel2, xb_sel3;
  logic [31:0] xb_out0, xb_out1, xb_out2, xb_out3;

  // ==========================================
  // 3. DUT INSTANTIATIONS
  // ==========================================
  handshake_sync #(8) dut63 (
      .clk_src(clk_fast), .rst_n_src(rst_n), .req_in(hs_req_in), .data_in(hs_data_in), .ready_src(hs_ready_src),
      .clk_dest(clk_slow), .rst_n_dest(rst_n), .ack_dest(hs_ack_dest), .req_dest(hs_req_dest), .data_out(hs_data_out)
  );

  async_fifo #(4, 8) dut66 (
      .wr_clk(clk_fast), .wr_rst_n(rst_n), .wr_en(fifo_wr_en), .wr_data(fifo_wr_data), .full(fifo_full),
      .rd_clk(clk_slow), .rd_rst_n(rst_n), .rd_en(fifo_rd_en), .rd_data(fifo_rd_data), .empty(fifo_empty)
  );

  // Note: Arbiters and Crossbars typically live in a single clock domain (the bus domain)
  matrix_arbiter dut69 (.clk(clk_fast), .rst_n(rst_n), .req(arb_req), .grant(arb_grant));

  crossbar_4x4 #(32) dut70 (
      .in0(xb_in0), .in1(xb_in1), .in2(xb_in2), .in3(xb_in3),
      .sel0(xb_sel0), .sel1(xb_sel1), .sel2(xb_sel2), .sel3(xb_sel3),
      .out0(xb_out0), .out1(xb_out1), .out2(xb_out2), .out3(xb_out3)
  );

  // ==========================================
  // 4. STIMULUS GENERATION
  // ==========================================
  initial begin
    $dumpfile("day7_sim.vcd");
    $dumpvars(0, tb_day7);

    // Initialize
    rst_n = 0;
    hs_req_in = 0; hs_data_in = 0; hs_ack_dest = 0;
    fifo_wr_en = 0; fifo_wr_data = 0; fifo_rd_en = 0;
    arb_req = 0;
    xb_in0 = 32'hAAAA_AAAA; xb_in1 = 32'hBBBB_BBBB; 
    xb_in2 = 32'hCCCC_CCCC; xb_in3 = 32'hDDDD_DDDD;
    xb_sel0 = 0; xb_sel1 = 0; xb_sel2 = 0; xb_sel3 = 0;

    #20 rst_n = 1;

    $display("\n=======================================");
    $display("STARTING DAY 7: CDC & ARBITRATION");
    $display("=======================================\n");

    // --- 66. Asynchronous FIFO Test ---
    $display(">> Writing to Async FIFO from Fast Domain (500MHz)...");
    @(posedge clk_fast);
    fifo_wr_en = 1; fifo_wr_data = 8'hC3; @(posedge clk_fast);
    fifo_wr_en = 1; fifo_wr_data = 8'hA5; @(posedge clk_fast);
    fifo_wr_en = 0;
    
    #30; // Wait for Gray pointers to synchronize across domains
    
    $display(">> Reading from Async FIFO in Slow Domain (100MHz)...");
    @(posedge clk_slow);
    fifo_rd_en = 1; @(posedge clk_slow);
    fifo_rd_en = 1; @(posedge clk_slow);
    fifo_rd_en = 0;

    // --- 69. Matrix Arbiter Test ---
    $display(">> Testing LRU Matrix Arbiter...");
    @(posedge clk_fast);
    arb_req = 4'b0101; // Devices 0 and 2 request
    @(posedge clk_fast);
    // Device 0 should win based on initial matrix priority
    if (arb_grant == 4'b0001) $display("   [PASS] Device 0 won arbitration!");
    
    arb_req = 4'b0101; // Devices 0 and 2 request AGAIN
    @(posedge clk_fast);
    // Device 2 should win now, because Device 0 just went!
    if (arb_grant == 4'b0100) $display("   [PASS] Device 2 won arbitration (LRU working)!");
    arb_req = 4'b0000;

    // --- 70. Crossbar Test ---
    $display(">> Routing Data through Crossbar...");
    xb_sel0 = 2'b11; // Route in3 (DDDD) to out0
    xb_sel2 = 2'b01; // Route in1 (BBBB) to out2
    #10;
    if (xb_out0 == 32'hDDDD_DDDD && xb_out2 == 32'hBBBB_BBBB)
        $display("   [PASS] Crossbar routing successful!");

    #50;
    $display("\n=======================================");
    $display("DAY 7 TESTS COMPLETED SUCCESSFULLY");
    $display("Run 'make wave' to see the Gray Pointers crossing clock domains!");
    $display("=======================================\n");
    
    $finish;
  end

endmodule

100-Days-of-SystemVerilog/Day07_CDC_Arbitration/day7_sim.vcd
$date
	Tue Mar 24 21:53:27 2026
$end
$version
	Icarus Verilog
$end
$timescale
	1ps
$end
$scope module tb_day7 $end
$var wire 32 ! xb_out3 [31:0] $end
$var wire 32 " xb_out2 [31:0] $end
$var wire 32 # xb_out1 [31:0] $end
$var wire 32 $ xb_out0 [31:0] $end
$var wire 1 % hs_req_dest $end
$var wire 1 & hs_ready_src $end
$var wire 8 ' hs_data_out [7:0] $end
$var wire 8 ( fifo_rd_data [7:0] $end
$var wire 1 ) fifo_full $end
$var wire 1 * fifo_empty $end
$var wire 4 + arb_grant [3:0] $end
$var reg 4 , arb_req [3:0] $end
$var reg 1 - clk_fast $end
$var reg 1 . clk_slow $end
$var reg 1 / fifo_rd_en $end
$var reg 8 0 fifo_wr_data [7:0] $end
$var reg 1 1 fifo_wr_en $end
$var reg 1 2 hs_ack_dest $end
$var reg 8 3 hs_data_in [7:0] $end
$var reg 1 4 hs_req_in $end
$var reg 1 5 rst_n $end
$var reg 32 6 xb_in0 [31:0] $end
$var reg 32 7 xb_in1 [31:0] $end
$var reg 32 8 xb_in2 [31:0] $end
$var reg 32 9 xb_in3 [31:0] $end
$var reg 2 : xb_sel0 [1:0] $end
$var reg 2 ; xb_sel1 [1:0] $end
$var reg 2 < xb_sel2 [1:0] $end
$var reg 2 = xb_sel3 [1:0] $end
$scope module dut63 $end
$var wire 1 2 ack_dest $end
$var wire 1 . clk_dest $end
$var wire 1 - clk_src $end
$var wire 8 > data_in [7:0] $end
$var wire 1 & ready_src $end
$var wire 1 % req_dest $end
$var wire 1 4 req_in $end
$var wire 1 5 rst_n_dest $end
$var wire 1 5 rst_n_src $end
$var reg 1 ? ack_sync1 $end
$var reg 1 @ ack_sync2 $end
$var reg 8 A data_out [7:0] $end
$var reg 1 B req_sync1 $end
$var reg 1 C req_sync2 $end
$upscope $end
$scope module dut66 $end
$var wire 1 . rd_clk $end
$var wire 1 / rd_en $end
$var wire 1 5 rd_rst_n $end
$var wire 1 - wr_clk $end
$var wire 8 D wr_data [7:0] $end
$var wire 1 1 wr_en $end
$var wire 1 5 wr_rst_n $end
$var wire 1 ) full $end
$var wire 1 * empty $end
$var reg 8 E rd_data [7:0] $end
$var reg 5 F rd_ptr_bin [4:0] $end
$var reg 5 G rd_ptr_gray [4:0] $end
$var reg 5 H rd_ptr_gray_next [4:0] $end
$var reg 5 I rd_ptr_gray_sync1 [4:0] $end
$var reg 5 J rd_ptr_gray_sync2 [4:0] $end
$var reg 5 K wr_ptr_bin [4:0] $end
$var reg 5 L wr_ptr_gray [4:0] $end
$var reg 5 M wr_ptr_gray_next [4:0] $end
$var reg 5 N wr_ptr_gray_sync1 [4:0] $end
$var reg 5 O wr_ptr_gray_sync2 [4:0] $end
$upscope $end
$scope module dut69 $end
$var wire 1 - clk $end
$var wire 4 P req [3:0] $end
$var wire 1 5 rst_n $end
$var reg 4 Q grant [3:0] $end
$var reg 4 R wins [3:0] $end
$upscope $end
$scope module dut70 $end
$var wire 32 S in0 [31:0] $end
$var wire 32 T in1 [31:0] $end
$var wire 32 U in2 [31:0] $end
$var wire 32 V in3 [31:0] $end
$var wire 2 W sel0 [1:0] $end
$var wire 2 X sel1 [1:0] $end
$var wire 2 Y sel2 [1:0] $end
$var wire 2 Z sel3 [1:0] $end
$var reg 32 [ out0 [31:0] $end
$var reg 32 \ out1 [31:0] $end
$var reg 32 ] out2 [31:0] $end
$var reg 32 ^ out3 [31:0] $end
$upscope $end
$upscope $end
$enddefinitions $end
#0
$dumpvars
b10101010101010101010101010101010 ^
b10101010101010101010101010101010 ]
b10101010101010101010101010101010 \
b10101010101010101010101010101010 [
b0 Z
b0 Y
b0 X
b0 W
b11011101110111011101110111011101 V
b11001100110011001100110011001100 U
b10111011101110111011101110111011 T
b10101010101010101010101010101010 S
b0 R
b0 Q
b0 P
b0 O
b0 N
b1 M
b0 L
b0 K
b0 J
b0 I
b1 H
b0 G
b0 F
b0 E
b0 D
0C
0B
b0 A
0@
0?
b0 >
b0 =
b0 <
b0 ;
b0 :
b11011101110111011101110111011101 9
b11001100110011001100110011001100 8
b10111011101110111011101110111011 7
b10101010101010101010101010101010 6
05
04
b0 3
02
01
b0 0
0/
0.
0-
b0 ,
b0 +
1*
0)
b0 (
b0 '
1&
0%
b10101010101010101010101010101010 $
b10101010101010101010101010101010 #
b10101010101010101010101010101010 "
b10101010101010101010101010101010 !
$end
#1000
1-
#2000
0-
#3000
1-
#4000
0-
#5000
1-
1.
#6000
0-
#7000
1-
#8000
0-
#9000
1-
#10000
0-
0.
#11000
1-
#12000
0-
#13000
1-
#14000
0-
#15000
1-
1.
#16000
0-
#17000
1-
#18000
0-
#19000
1-
#20000
0-
0.
15
#21000
b11 M
b1 L
b1 K
b11000011 0
b11000011 D
11
1-
#22000
0-
#23000
b10 M
b11 L
b10 K
b10100101 0
b10100101 D
1-
#24000
0-
#25000
b11 N
01
1-
1.
#26000
0-
#27000
1-
#28000
0-
#29000
1-
#30000
0-
0.
#31000
1-
#32000
0-
#33000
1-
#34000
0-
#35000
0*
b11 O
1-
1.
#36000
0-
#37000
1-
#38000
0-
#39000
1-
#40000
0-
0.
#41000
1-
#42000
0-
#43000
1-
#44000
0-
#45000
1-
1.
#46000
0-
#47000
1-
#48000
0-
#49000
1-
#50000
0-
0.
#51000
1-
#52000
0-
#53000
1-
#54000
0-
#55000
b11 H
b1 G
b1 F
b11000011 (
b11000011 E
1/
1-
1.
#56000
0-
#57000
b1 I
1-
#58000
0-
#59000
b1 J
1-
#60000
0-
0.
#61000
1-
#62000
0-
#63000
1-
#64000
0-
#65000
b10 H
1*
b11 G
b10 F
b10100101 (
b10100101 E
1-
1.
#66000
0-
#67000
b11 I
1-
#68000
0-
#69000
b11 J
1-
#70000
0-
0.
#71000
1-
#72000
0-
#73000
1-
#74000
0-
#75000
0/
1-
1.
#76000
0-
#77000
b1 +
b1 Q
b1 R
b101 ,
b101 P
1-
#78000
0-
#79000
b100 R
b100 +
b100 Q
1-
#80000
0-
0.
#81000
b10111011101110111011101110111011 "
b10111011101110111011101110111011 ]
b11011101110111011101110111011101 $
b11011101110111011101110111011101 [
b0 R
b0 +
b0 Q
b1 <
b1 Y
b11 :
b11 W
b0 ,
b0 P
1-
